pynord/__init__.py
pynord/pynord.py
pynord/util.py
pynord-1.0.0.dist-info/LICENSE
pynord-1.0.0.dist-info/METADATA
pynord-1.0.0.dist-info/WHEEL
pynord-1.0.0.dist-info/top_level.txt
pynord-1.0.0.dist-info/RECORD
