Metadata-Version: 2.1
Name: pynord
Version: 1.0.0
Summary: A Python library for NordVPN on Linux.
Author: thebrightlizard
Author-email: <maria.gonzalez5884@outlook.com>
Keywords: python,nordvpn,vpn,webscraping,privacy
Classifier: Development Status :: 1 - Planning
Classifier: Intended Audience :: Developers
Classifier: Programming Language :: Python :: 3
Classifier: Operating System :: Unix
License-File: LICENSE
